binary_magic_squares/__init__.py
binary_magic_squares/core.py
binary_magic_squares/pytorch.py
binary_magic_squares-0.1.0.dist-info/LICENSE.md
binary_magic_squares-0.1.0.dist-info/METADATA
binary_magic_squares-0.1.0.dist-info/WHEEL
binary_magic_squares-0.1.0.dist-info/top_level.txt
binary_magic_squares-0.1.0.dist-info/RECORD
