Metadata-Version: 2.1
Name: binary-magic-squares
Version: 0.1.0
Summary: Generate Binary Magic Squares
Author-email: Alain Riou <alain.riou@sony.com>
Project-URL: source, https://github.com/aRI0U/binary-magic-squares
Classifier: Development Status :: 3 - Alpha
Classifier: Intended Audience :: Developers
Classifier: License :: OSI Approved :: GNU Lesser General Public License v3 (LGPLv3)
Classifier: Programming Language :: Python :: 3.8
Classifier: Programming Language :: Python :: 3.9
Classifier: Programming Language :: Python :: 3.10
Classifier: Programming Language :: Python :: 3.11
Requires-Python: >=3.8
License-File: LICENSE.md
Requires-Dist: numpy
Provides-Extra: pytorch
Requires-Dist: torch ; extra == 'pytorch'
Provides-Extra: test
Requires-Dist: pytest ; extra == 'test'
